robots/__init__.py
robots/admin.py
robots/apps.py
robots/forms.py
robots/models.py
robots/settings.py
robots/tests.py
robots/urls.py
robots/views.py
robots/locale/da/LC_MESSAGES/django.mo
robots/locale/da/LC_MESSAGES/django.po
robots/locale/de/LC_MESSAGES/django.mo
robots/locale/de/LC_MESSAGES/django.po
robots/locale/el/LC_MESSAGES/django.mo
robots/locale/el/LC_MESSAGES/django.po
robots/locale/en/LC_MESSAGES/django.mo
robots/locale/en/LC_MESSAGES/django.po
robots/locale/es_ES/LC_MESSAGES/django.mo
robots/locale/es_ES/LC_MESSAGES/django.po
robots/locale/fr/LC_MESSAGES/django.mo
robots/locale/fr/LC_MESSAGES/django.po
robots/locale/it/LC_MESSAGES/django.mo
robots/locale/it/LC_MESSAGES/django.po
robots/locale/ja/LC_MESSAGES/django.mo
robots/locale/ja/LC_MESSAGES/django.po
robots/locale/nl/LC_MESSAGES/django.mo
robots/locale/nl/LC_MESSAGES/django.po
robots/locale/pt_BR/LC_MESSAGES/django.mo
robots/locale/pt_BR/LC_MESSAGES/django.po
robots/locale/ru/LC_MESSAGES/django.mo
robots/locale/ru/LC_MESSAGES/django.po
robots/locale/sk/LC_MESSAGES/django.mo
robots/locale/sk/LC_MESSAGES/django.po
robots/locale/uk/LC_MESSAGES/django.mo
robots/locale/uk/LC_MESSAGES/django.po
robots/migrations/0001_initial.py
robots/migrations/0002_alter_id_fields.py
robots/migrations/__init__.py
robots/templates/robots/rule_list.html
django_robots-6.0.dist-info/LICENSE.txt
django_robots-6.0.dist-info/METADATA
django_robots-6.0.dist-info/WHEEL
django_robots-6.0.dist-info/top_level.txt
django_robots-6.0.dist-info/RECORD
